yapona/__init__.py
yapona/app.py
yapona/dbus.py
yapona/focus.svg
yapona/main.py
yapona/timer.py
yapona/tomato.svg
yapona-0.1.2.dist-info/WHEEL
yapona-0.1.2.dist-info/entry_points.txt
yapona-0.1.2.dist-info/METADATA
yapona-0.1.2.dist-info/RECORD
